eebackup/__init__.py
eebackup/__main__.py
eebackup/config.py
eebackup/core.py
eebackup/fileformat.py
eebackup-0.1.1.dist-info/METADATA
eebackup-0.1.1.dist-info/WHEEL
eebackup-0.1.1.dist-info/entry_points.txt
eebackup-0.1.1.dist-info/top_level.txt
eebackup-0.1.1.dist-info/RECORD
