Metadata-Version: 2.4
Name: eebackup
Version: 0.1.1
Summary: An incremental backup program
Requires-Python: >=3.7
